{
    "firstAudio": {
      "sound": "df46a38a1445b300f1e0637400f4bd04",
      "soundAlias": "I_have_a_book_STS.mp3"
    },
    "detail": "",
    "pages": [
      {
        "msg": 0,
        "sound": "5cb4916ada496006405ee562735d16bd",
        "soundAlias": "airplane_B2U3.mp3",
        "question": {
          "text": "airplane%20",
          "image": "",
          "imageAlias": "",
          "sound": "5cb4916ada496006405ee562735d16bd",
          "soundAlias": "airplane_B2U3.mp3",
          "isSplit": false
        }
      },
      {
        "msg": 0,
        "sound": "333e7f654db518ae6239b31e71f7e28f",
        "soundAlias": "fish.mp3",
        "question": {
          "text": "grapes%20hao%20chi%20",
          "image": "",
          "imageAlias": "",
          "sound": "ef479343d27a11d961cbb2a0c9c48974",
          "soundAlias": "grapes_B2U1.mp3",
          "isSplit": true
        }
      },
      {
        "msg": 0,
        "sound": "af614cdeb19335daef1a59f69e1e4330",
        "soundAlias": "How_about_you_SW.mp3",
        "question": {
          "text": "%20panda%20",
          "image": "f5084b4d807acf28120b4c0511112b8b",
          "imageAlias": "panda.png",
          "sound": "fc796910523ff97b27f6b2df0eb1b126",
          "soundAlias": "panda_LAS_MMC.mp3",
          "isSplit": false
        }
      },
      {
        "msg": 0,
        "sound": "733df7b02c947e038957306d8d1ea544",
        "soundAlias": "The_Prize_STP2_The_quiz_is_on_frogs.mp3",
        "question": {
          "text": "fish%20hop%20",
          "image": "",
          "imageAlias": "",
          "sound": "333e7f654db518ae6239b31e71f7e28f",
          "soundAlias": "fish.mp3",
          "isSplit": false
        }
      },
      {
        "msg": 0,
        "sound": "af614cdeb19335daef1a59f69e1e4330",
        "soundAlias": "How_about_you_SW.mp3",
        "question": {
          "text": "asdf%20asdf%20asdf%20",
          "image": "e0ed270b4f99dc3cdcb1e6085572097d",
          "imageAlias": "cow_B3U1_LTW.png",
          "sound": "694a3c55166dac4061f93d68762c7403",
          "soundAlias": "cow.mp3",
          "isSplit": true
        }
      },
      {
        "msg": 0,
        "sound": "af614cdeb19335daef1a59f69e1e4330",
        "soundAlias": "How_about_you_SW.mp3",
        "question": {
          "text": "apple%20sdd%20",
          "image": "08a96c18c97e1869f27c7b147a85b58c",
          "imageAlias": "apple_B2U1_LTW.png",
          "sound": "3769fcd9ec153d31988c3a25555552c8",
          "soundAlias": "apple_B2U1.mp3",
          "isSplit": false
        }
      }
      
    ]
  }
