{
  "detail": "",
  "firstAudio": {
    "sound": "58e4dac9ee8668e697c0b4b30a937e21"
  },
  "questions": [{
      "text": "who's your daddy who's your daddy?who's your daddy who's your daddy who's your daddy who's your daddy",
      "sound": "58e4dac9ee8668e697c0b4b30a937e21",
      "duration": 15
    },
    {
      "text": "what's your name?",
      "sound": "b1b1e06c0dc5058783f3d43c23526a16",
      "duration": 15
    },
    {
      "text": "that's great",
      "sound": "b1b1e06c0dc5058783f3d43c23526a16",
      "duration": 15
    }
  ]
}